unifiedfinder/__init__.py
unifiedfinder/finder.py
unifiedfinder-1.1.0.dist-info/LICENSE
unifiedfinder-1.1.0.dist-info/METADATA
unifiedfinder-1.1.0.dist-info/WHEEL
unifiedfinder-1.1.0.dist-info/top_level.txt
unifiedfinder-1.1.0.dist-info/RECORD
