Metadata-Version: 2.2
Name: unifiedfinder
Version: 1.1.0
Summary: A unified scraping helper combining BeautifulSoup and Selenium utilities.
Home-page: https://github.com/Trollparts/unifiedfinder
Author: Trollparts
Classifier: Programming Language :: Python :: 3
Classifier: License :: OSI Approved :: MIT License
Requires-Python: >=3.6
License-File: LICENSE
Requires-Dist: beautifulsoup4
Requires-Dist: selenium
Requires-Dist: requests
Dynamic: author
Dynamic: classifier
Dynamic: description
Dynamic: description-content-type
Dynamic: home-page
Dynamic: requires-dist
Dynamic: requires-python
Dynamic: summary
